Metadata-Version: 2.1
Name: us2pycognito
Version: 2021.11.1
Summary: Python class to integrate Boto3's Cognito client so it is easy to login users. With SRP support.
Home-page: https://github.com/pvizeli/pycognito
Author: Pascal Vizeli
Author-email: pvizeli@syshack.ch
License: Apache License 2.0
Download-URL: https://github.com/pvizeli/pycognito/tarball/2021.11.1
Keywords: aws,cognito,api,gateway,serverless
Platform: UNKNOWN
Classifier: Programming Language :: Python :: 3.6
Classifier: Programming Language :: Python :: 3.7
Classifier: Programming Language :: Python :: 3.8
Classifier: Topic :: Software Development :: Libraries :: Python Modules
Classifier: Environment :: Web Environment
License-File: LICENSE
